<Alloy>
	<Window id="EventWindow">
		<LeftNavButton platform="ios" formFactor="tablet"><View></View></LeftNavButton>
		
		<RightNavButton platform="ios">
			<ImageView id="Reminder" image="/images/icon_reminder.png" width="28" height="28" onClick="toggleReminder" />
		</RightNavButton>
		
		<Menu id="Reminder" platform="android">
			<MenuItem title="Set Reminder" showAsAction="Ti.Android.SHOW_AS_ACTION_NEVER" onClick="toggleReminder" />
		</Menu>
		
		<View class="imageContainer">
			<ImageView id="Image" platform="ios" />
			<View id="Image" platform="android" />
			<View class="imageOverlay" />
		</View>
		
		<ScrollView id="ScrollView">
			<View id="Content">
				<Label id="Title" />
				
				<View class="details">
					<View class="left">
						<Label id="Date" platform="ios" formFactor="tablet" />
						<Label id="Time" />
						<Label id="Subkast" />
					</View>
					
					<View class="right">
						<Button id="Share" title="Share Event" />
						
						<View id="Upvote">
							<ImageView class="upvoteArrow" />
							<Label id="UpvoteCount" text="0" />
						</View>
					</View>
				</View>
				
				<View class="details">
					<View class="left">
						<Label id="TimeFromNow" />
					</View>
					
					<View class="right">
						<Label id="Author" />
					</View>
				</View>
				
				<!-- Dynamically created description goes here -->
			</View>
			
			<View id="Comments">
				<!--
				// TODO: v1.2
				<View class="commentBoxWrapper">
					<TextArea id="CommentBox" value="\nLeave a comment..." />
				</View>
				
				<Button id="CommentSubmit" title="Comment" platform="android" />
				-->
				
				<View id="CommentsContainer"></View>
			</View>
		</ScrollView>
		
		<View class="navbarOverlay" />
	</Window>
</Alloy>